tr0nz0d/__init__.py
tr0nz0d/discord_tools/__init__.py
tr0nz0d/discord_tools/tools.py
tr0nz0d/django_tools/__init__.py
tr0nz0d/django_tools/tools.py
tr0nz0d/security/__init__.py
tr0nz0d/security/criptografia.py
tr0nz0d/security/pswd.py
tr0nz0d/tests/__init__.py
tr0nz0d/tests/manual_testing.py
tr0nz0d/tests/test_discord_tools.py
tr0nz0d/tests/test_django_tools.py
tr0nz0d/tests/test_math_tools.py
tr0nz0d/tests/test_random_tools.py
tr0nz0d/tests/test_security_criptografia.py
tr0nz0d/tests/test_security_pswd.py
tr0nz0d/tests/test_tools_cnpj.py
tr0nz0d/tests/test_tools_cpf.py
tr0nz0d/tests/test_tools_generics.py
tr0nz0d/tests/test_tools_logging.py
tr0nz0d/tests/test_tools_text.py
tr0nz0d/tools/__init__.py
tr0nz0d/tools/cnpj.py
tr0nz0d/tools/cpf.py
tr0nz0d/tools/generics.py
tr0nz0d/tools/logging.py
tr0nz0d/tools/math_tools.py
tr0nz0d/tools/random_tools.py
tr0nz0d/tools/text.py
tr0nz0d-0.1.6.dist-info/LICENSE
tr0nz0d-0.1.6.dist-info/METADATA
tr0nz0d-0.1.6.dist-info/WHEEL
tr0nz0d-0.1.6.dist-info/top_level.txt
tr0nz0d-0.1.6.dist-info/RECORD
