Metadata-Version: 2.1
Name: tr0nz0d
Version: 0.1.6
Summary: TR0NZ0D Lib is a library created in python to facilitate the use of some tools.
Author: Gabriel Menezes de Antonio
License: MIT
Project-URL: Source, https://github.com/TR0NZ0D/TR0NZ0D_Lib
Project-URL: Bug Tracker, https://github.com/TR0NZ0D/TR0NZ0D_Lib/issues
Keywords: tronzod,tr0nz0d,TR0NZ0D,TRONZOD,tools
Classifier: Programming Language :: Python :: 3.10
Classifier: Programming Language :: Python :: 3.11
Classifier: License :: OSI Approved :: MIT License
Classifier: Operating System :: OS Independent
Classifier: Development Status :: 4 - Beta
Classifier: Environment :: No Input/Output (Daemon)
Classifier: Intended Audience :: Developers
Classifier: Natural Language :: Portuguese (Brazilian)
Classifier: Topic :: Utilities
Classifier: Topic :: Software Development
Classifier: Topic :: Security :: Cryptography
Classifier: Topic :: Printing
Classifier: Topic :: System :: Logging
Requires-Python: >=3.10
License-File: LICENSE
Requires-Dist: cryptography
Requires-Dist: requests
Requires-Dist: python-dateutil
